paddleocr_mcp/__init__.py
paddleocr_mcp/__main__.py
paddleocr_mcp/pipelines.py
paddleocr_mcp/py.typed
paddleocr_mcp-0.4.1.dist-info/METADATA
paddleocr_mcp-0.4.1.dist-info/WHEEL
paddleocr_mcp-0.4.1.dist-info/entry_points.txt
paddleocr_mcp-0.4.1.dist-info/top_level.txt
paddleocr_mcp-0.4.1.dist-info/RECORD
