Metadata-Version: 2.4
Name: paddleocr_mcp
Version: 0.4.1
Requires-Python: >=3.10
Requires-Dist: mcp>=1.5.0
Requires-Dist: fastmcp>=2.0.0
Requires-Dist: httpx>=0.24.0
Requires-Dist: numpy>=1.24.0
Requires-Dist: pillow>=9.0.0
Requires-Dist: puremagic>=1.30.0
Requires-Dist: typing-extensions>=4.0.0
Provides-Extra: local
Requires-Dist: paddleocr[doc-parser]>=3.2; extra == "local"
Provides-Extra: local-cpu
Requires-Dist: paddleocr[doc-parser]>=3.2; extra == "local-cpu"
Requires-Dist: paddlepaddle>=3.0.0; extra == "local-cpu"
